media_pumpkin/ClassificationModule.py
media_pumpkin/ColorModule.py
media_pumpkin/FPS.py
media_pumpkin/FaceDetectionModule.py
media_pumpkin/FaceMeshModule.py
media_pumpkin/HandTrackingModule.py
media_pumpkin/PIDModule.py
media_pumpkin/PlotModule.py
media_pumpkin/PoseModule.py
media_pumpkin/SelfiSegmentationModule.py
media_pumpkin/SerialModule.py
media_pumpkin/Utils.py
media_pumpkin/__init__.py
media_pumpkin-0.1.dist-info/licenses/LICENSE.txt
media_pumpkin-0.1.dist-info/METADATA
media_pumpkin-0.1.dist-info/WHEEL
media_pumpkin-0.1.dist-info/top_level.txt
media_pumpkin-0.1.dist-info/RECORD
