Metadata-Version: 2.4
Name: media_pumpkin
Version: 0.1
Summary: Computer Vision Helping Library
Home-page: https://github.com/SmugPumpkins/media-py
Author: SmugPumpkins
License: MIT
Keywords: ComputerVision,HandTracking,FaceTracking,PoseEstimation
Classifier: Development Status :: 3 - Alpha
Classifier: Intended Audience :: Developers
Classifier: Topic :: Software Development :: Build Tools
Classifier: License :: OSI Approved :: MIT License
Classifier: Programming Language :: Python :: 3
Requires-Python: >=3.6
License-File: LICENSE.txt
Requires-Dist: opencv-python
Requires-Dist: numpy
Dynamic: author
Dynamic: classifier
Dynamic: home-page
Dynamic: keywords
Dynamic: license
Dynamic: license-file
Dynamic: requires-dist
Dynamic: requires-python
Dynamic: summary
